stocksnap/__init__.py
stocksnap/stocksnap.py
stocksnap/util/__init__.py
stocksnap/util/google_finance_extraction.py
stocksnap-0.1.1.dist-info/METADATA
stocksnap-0.1.1.dist-info/WHEEL
stocksnap-0.1.1.dist-info/top_level.txt
stocksnap-0.1.1.dist-info/RECORD
