Metadata-Version: 2.1
Name: stocksnap
Version: 0.1.1
Summary: Fetch stock data via Google Finance
Home-page: https://github.com/omrawal/Stock-Snap
Author: Om Rawal
Author-email: omrawal2801@gmail.com
Keywords: python,stock,BSE,API,NSE,scraping,web scraping
Classifier: Development Status :: 3 - Alpha
Classifier: Intended Audience :: Developers
Classifier: Programming Language :: Python :: 3
Classifier: Operating System :: Unix
Classifier: Operating System :: MacOS :: MacOS X
Classifier: Operating System :: Microsoft :: Windows
Requires-Dist: beautifulsoup4
Requires-Dist: requests
Requires-Dist: bs4
Requires-Dist: urllib3
